LICENSE
MANIFEST.in
README.md
requirements.txt
setup.py
details/__init__.py
details/_version
details/costs.py
details.egg-info/PKG-INFO
details.egg-info/SOURCES.txt
details.egg-info/dependency_links.txt
details.egg-info/top_level.txt