Metadata-Version: 1.1
Name: details
Version: 0.2.0
Summary: Tools for processing AWS detailed billing reports
Home-page: https://github.com/scopely-devops/details
Author: Mitch Garnaat
Author-email: mitch@scopely.com
License: Apache License
